wmss/__init__.py
wmss/_version.py
wmss/sampler.py
wmss/setup.py
wmss-0.1.3.dist-info/LICENSE.txt
wmss-0.1.3.dist-info/METADATA
wmss-0.1.3.dist-info/WHEEL
wmss-0.1.3.dist-info/top_level.txt
wmss-0.1.3.dist-info/RECORD
