Metadata-Version: 2.1
Name: wmss
Version: 0.1.3
Summary: WMSS Library
Author-email: Angel Marques Mateu <amarques@cgf.upv.es>
Classifier: Programming Language :: Python :: 3.8
Classifier: License :: OSI Approved :: GNU General Public License v3 (GPLv3)
Classifier: Operating System :: OS Independent
Requires-Python: >=3.8
License-File: LICENSE.txt
Requires-Dist: easygui
Requires-Dist: OWSLib
Requires-Dist: pyproj
Requires-Dist: pyshp
